[{"rut":"111111111", "clave":"1111", "id":1},
  {"rut":"212767204", "clave":"clave", "id":2},
  {"rut":"20234478k", "clave":"12345", "id":3},
  {"rut":"123456785", "clave":"pass", "id":4},
  {"rut":"123456793", "clave":"123", "id":5},
  {"rut":"123456807", "clave":"123", "id":6},
  {"rut":"123456815", "clave":"123", "id":7},
  {"rut":"123456823", "clave":"123", "id":8},
  {"rut":"123456785", "clave":"123", "id":9},
  {"rut":"12345684k", "clave":"123", "id":10},
  {"rut":"123456858", "clave":"123", "id":11},
  {"rut":"123456866", "clave":"123", "id":12},
  {"rut":"123456874", "clave":"123", "id":13},
  {"rut":"123456882", "clave":"123", "id":14},
  {"rut":"123456890", "clave":"123", "id":15},
  {"rut":"123456904", "clave":"123", "id":16},
  {"rut":"123456912", "clave":"123", "id":17},
  {"rut":"123456920", "clave":"123", "id":18},
  {"rut":"123456939", "clave":"123", "id":19},
  {"rut":"123456947", "clave":"123", "id":20},
  {"rut":"123456955", "clave":"123", "id":21},
  {"rut":"123456963", "clave":"123", "id":22},
  {"rut":"123456971", "clave":"123", "id":23},
  {"rut":"12345698k", "clave":"123", "id":24},
  {"rut":"123456998", "clave":"123", "id":25},
  {"rut":"123457005", "clave":"123", "id":26},
  {"rut":"123457013", "clave":"123", "id":27},
  {"rut":"123457021", "clave":"123", "id":28},
  {"rut":"12345703k", "clave":"123", "id":29},
  {"rut":"123457048", "clave":"123", "id":30},
  {"rut":"123457056", "clave":"123", "id":31},
  {"rut":"123457064", "clave":"123", "id":32},
  {"rut":"123457072", "clave":"123", "id":33},
  {"rut":"123457080", "clave":"123", "id":34},
  {"rut":"123457099", "clave":"123", "id":35},
  {"rut":"123457102", "clave":"123", "id":36},
  {"rut":"123457110", "clave":"123", "id":37},
  {"rut":"123457129", "clave":"123", "id":38},
  {"rut":"123457137", "clave":"123", "id":39},
  {"rut":"123457145", "clave":"123", "id":40},
  {"rut":"123457153", "clave":"123", "id":41},
  {"rut":"123457161", "clave":"123", "id":42},
  {"rut":"12345717k", "clave":"123", "id":43},
  {"rut":"123457188", "clave":"123", "id":44},
  {"rut":"123457196", "clave":"123", "id":45},
  {"rut":"12345720k", "clave":"123", "id":46},
  {"rut":"123457218", "clave":"123", "id":47},
  {"rut":"123457226", "clave":"123", "id":48},
  {"rut":"123457234", "clave":"123", "id":49},
  {"rut":"123457242", "clave":"123", "id":50},
  {"rut":"123457250", "clave":"123", "id":51},
  {"rut":"123457269", "clave":"123", "id":52},
  {"rut":"123457277", "clave":"123", "id":53},
  {"rut":"123457285", "clave":"123", "id":54},
  {"rut":"123457293", "clave":"123", "id":55},
  {"rut":"123457307", "clave":"123", "id":56},
  {"rut":"123457315", "clave":"123", "id":57},
  {"rut":"123457323", "clave":"123", "id":58},
  {"rut":"123457331", "clave":"123", "id":59},
  {"rut":"12345734k", "clave":"123", "id":60},
  {"rut":"123457358", "clave":"123", "id":61},
  {"rut":"123457366", "clave":"123", "id":62},
  {"rut":"123457374", "clave":"123", "id":63},
  {"rut":"123457382", "clave":"123", "id":64},
  {"rut":"123457390", "clave":"123", "id":65},
  {"rut":"123457404", "clave":"123", "id":66},
  {"rut":"123457412", "clave":"123", "id":67},
  {"rut":"123457420", "clave":"123", "id":68},
  {"rut":"123457439", "clave":"123", "id":69},
  {"rut":"123457447", "clave":"123", "id":70},
  {"rut":"123457455", "clave":"123", "id":71},
  {"rut":"123457463", "clave":"123", "id":72},
  {"rut":"123457471", "clave":"123", "id":73},
  {"rut":"12345748k", "clave":"123", "id":74},
  {"rut":"123457498", "clave":"123", "id":75},
  {"rut":"123457501", "clave":"123", "id":76},
  {"rut":"12345751k", "clave":"123", "id":77},
  {"rut":"123457528", "clave":"123", "id":78},
  {"rut":"123457536", "clave":"123", "id":79},
  {"rut":"123457544", "clave":"123", "id":80},
  {"rut":"123457552", "clave":"123", "id":81},
  {"rut":"123457560", "clave":"123", "id":82},
  {"rut":"123457579", "clave":"123", "id":83},
  {"rut":"123457587", "clave":"123", "id":84},
  {"rut":"123457595", "clave":"123", "id":85},
  {"rut":"123457609", "clave":"123", "id":86},
  {"rut":"123457617", "clave":"123", "id":87},
  {"rut":"123457625", "clave":"123", "id":88},
  {"rut":"123457633", "clave":"123", "id":89},
  {"rut":"123457641", "clave":"123", "id":90},
  {"rut":"12345765k", "clave":"123", "id":91},
  {"rut":"123457668", "clave":"123", "id":92},
  {"rut":"123457676", "clave":"123", "id":93},
  {"rut":"123457684", "clave":"123", "id":94},
  {"rut":"123457692", "clave":"123", "id":95},
  {"rut":"123457706", "clave":"123", "id":96},
  {"rut":"123457714", "clave":"123", "id":97},
  {"rut":"123457722", "clave":"123", "id":98},
  {"rut":"123457730", "clave":"123", "id":99},
  {"rut":"123457749", "clave":"123", "id":100},
  {"rut":"123457757", "clave":"123", "id":101},
  {"rut":"123457765", "clave":"123", "id":102},
  {"rut":"123457773", "clave":"123", "id":103},
  {"rut":"123457781", "clave":"123", "id":104},
  {"rut":"12345779k", "clave":"123", "id":105},
  {"rut":"123457803", "clave":"123", "id":106},
  {"rut":"123457811", "clave":"123", "id":107},
  {"rut":"12345782k", "clave":"123", "id":108},
  {"rut":"123457838", "clave":"123", "id":109},
  {"rut":"123457846", "clave":"123", "id":110},
  {"rut":"123457854", "clave":"123", "id":111},
  {"rut":"123457862", "clave":"123", "id":112},
  {"rut":"123457870", "clave":"123", "id":113},
  {"rut":"123457889", "clave":"123", "id":114},
  {"rut":"123457897", "clave":"123", "id":115},
  {"rut":"123457900", "clave":"123", "id":116},
  {"rut":"123457919", "clave":"123", "id":117},
  {"rut":"123457927", "clave":"123", "id":118},
  {"rut":"123457935", "clave":"123", "id":119},
  {"rut":"123457943", "clave":"123", "id":120},
  {"rut":"123457951", "clave":"123", "id":121},
  {"rut":"12345796k", "clave":"123", "id":122},
  {"rut":"123457978", "clave":"123", "id":123},
  {"rut":"123457986", "clave":"123", "id":124},
  {"rut":"123457994", "clave":"123", "id":125},
  {"rut":"123458001", "clave":"123", "id":126},
  {"rut":"12345801k", "clave":"123", "id":127},
  {"rut":"123458028", "clave":"123", "id":128},
  {"rut":"123458036", "clave":"123", "id":129},
  {"rut":"123458044", "clave":"123", "id":130},
  {"rut":"123458052", "clave":"123", "id":131},
  {"rut":"123458060", "clave":"123", "id":132},
  {"rut":"123458079", "clave":"123", "id":133},
  {"rut":"123458087", "clave":"123", "id":134},
  {"rut":"123458095", "clave":"123", "id":135},
  {"rut":"123458109", "clave":"123", "id":136},
  {"rut":"123458117", "clave":"123", "id":137},
  {"rut":"123458125", "clave":"123", "id":138},
  {"rut":"123458133", "clave":"123", "id":139},
  {"rut":"123458141", "clave":"123", "id":140},
  {"rut":"12345815k", "clave":"123", "id":141},
  {"rut":"123458168", "clave":"123", "id":142},
  {"rut":"123458176", "clave":"123", "id":143},
  {"rut":"123458184", "clave":"123", "id":144},
  {"rut":"123458192", "clave":"123", "id":145},
  {"rut":"123458206", "clave":"123", "id":146},
  {"rut":"123458214", "clave":"123", "id":147},
  {"rut":"123458222", "clave":"123", "id":148},
  {"rut":"123458230", "clave":"123", "id":149},
  {"rut":"123458249", "clave":"123", "id":150},
  {"rut":"123458257", "clave":"123", "id":151},
  {"rut":"123458265", "clave":"123", "id":152},
  {"rut":"123458273", "clave":"123", "id":153},
  {"rut":"123458281", "clave":"123", "id":154},
  {"rut":"12345829k", "clave":"123", "id":155},
  {"rut":"123458303", "clave":"123", "id":156},
  {"rut":"123458311", "clave":"123", "id":157},
  {"rut":"12345832k", "clave":"123", "id":158},
  {"rut":"123458338", "clave":"123", "id":159},
  {"rut":"123458346", "clave":"123", "id":160},
  {"rut":"123458354", "clave":"123", "id":161},
  {"rut":"123458362", "clave":"123", "id":162},
  {"rut":"123458370", "clave":"123", "id":163},
  {"rut":"123458389", "clave":"123", "id":164},
  {"rut":"123458397", "clave":"123", "id":165},
  {"rut":"123458400", "clave":"123", "id":166},
  {"rut":"123458419", "clave":"123", "id":167},
  {"rut":"123458427", "clave":"123", "id":168},
  {"rut":"123458435", "clave":"123", "id":169},
  {"rut":"123458443", "clave":"123", "id":170},
  {"rut":"123458451", "clave":"123", "id":171},
  {"rut":"12345846k", "clave":"123", "id":172},
  {"rut":"123458478", "clave":"123", "id":173},
  {"rut":"123458486", "clave":"123", "id":174},
  {"rut":"123458494", "clave":"123", "id":175},
  {"rut":"123458508", "clave":"123", "id":176},
  {"rut":"123458516", "clave":"123", "id":177},
  {"rut":"123458524", "clave":"123", "id":178},
  {"rut":"123458532", "clave":"123", "id":179},
  {"rut":"123458540", "clave":"123", "id":180},
  {"rut":"123458559", "clave":"123", "id":181},
  {"rut":"123458567", "clave":"123", "id":182},
  {"rut":"123458575", "clave":"123", "id":183},
  {"rut":"123458583", "clave":"123", "id":184},
  {"rut":"123458591", "clave":"123", "id":185},
  {"rut":"123458605", "clave":"123", "id":186},
  {"rut":"123458613", "clave":"123", "id":187},
  {"rut":"123458621", "clave":"123", "id":188},
  {"rut":"12345863k", "clave":"123", "id":189},
  {"rut":"123458648", "clave":"123", "id":190},
  {"rut":"123458656", "clave":"123", "id":191},
  {"rut":"123458664", "clave":"123", "id":192},
  {"rut":"123458672", "clave":"123", "id":193},
  {"rut":"123458680", "clave":"123", "id":194},
  {"rut":"123458699", "clave":"123", "id":195},
  {"rut":"123458702", "clave":"123", "id":196},
  {"rut":"123458710", "clave":"123", "id":197},
  {"rut":"123458729", "clave":"123", "id":198},
  {"rut":"123458737", "clave":"123", "id":199},
  {"rut":"123458745", "clave":"123", "id":200},
  {"rut":"123458753", "clave":"123", "id":201},
  {"rut":"123458761", "clave":"123", "id":202},
  {"rut":"12345877k", "clave":"123", "id":203},
  {"rut":"123458788", "clave":"123", "id":204},
  {"rut":"123458796", "clave":"123", "id":205},
  {"rut":"12345880k", "clave":"123", "id":206},
  {"rut":"123458818", "clave":"123", "id":207},
  {"rut":"123458826", "clave":"123", "id":208},
  {"rut":"123458834", "clave":"123", "id":209},
  {"rut":"123458842", "clave":"123", "id":210},
  {"rut":"123458850", "clave":"123", "id":211},
  {"rut":"123458869", "clave":"123", "id":212},
  {"rut":"123458877", "clave":"123", "id":213},
  {"rut":"123458885", "clave":"123", "id":214},
  {"rut":"123458893", "clave":"123", "id":215},
  {"rut":"123458907", "clave":"123", "id":216},
  {"rut":"123458915", "clave":"123", "id":217},
  {"rut":"123458923", "clave":"123", "id":218},
  {"rut":"123458931", "clave":"123", "id":219},
  {"rut":"12345894k", "clave":"123", "id":220},
  {"rut":"123458958", "clave":"123", "id":221},
  {"rut":"123458966", "clave":"123", "id":222},
  {"rut":"123458974", "clave":"123", "id":223},
  {"rut":"123458982", "clave":"123", "id":224},
  {"rut":"123458990", "clave":"123", "id":225},
  {"rut":"123459008", "clave":"123", "id":226},
  {"rut":"123459016", "clave":"123", "id":227},
  {"rut":"123459024", "clave":"123", "id":228},
  {"rut":"123459032", "clave":"123", "id":229},
  {"rut":"123459040", "clave":"123", "id":230},
  {"rut":"123459059", "clave":"123", "id":231},
  {"rut":"123459067", "clave":"123", "id":232},
  {"rut":"123459075", "clave":"123", "id":233},
  {"rut":"123459083", "clave":"123", "id":234},
  {"rut":"123459091", "clave":"123", "id":235},
  {"rut":"123459105", "clave":"123", "id":236},
  {"rut":"123459113", "clave":"123", "id":237},
  {"rut":"123459121", "clave":"123", "id":238},
  {"rut":"12345913k", "clave":"123", "id":239},
  {"rut":"123459148", "clave":"123", "id":240},
  {"rut":"123459156", "clave":"123", "id":241},
  {"rut":"123459164", "clave":"123", "id":242},
  {"rut":"123459172", "clave":"123", "id":243},
  {"rut":"123459180", "clave":"123", "id":244},
  {"rut":"123459199", "clave":"123", "id":245},
  {"rut":"123459202", "clave":"123", "id":246},
  {"rut":"123459210", "clave":"123", "id":247},
  {"rut":"123459229", "clave":"123", "id":248},
  {"rut":"123459237", "clave":"123", "id":249},
  {"rut":"123459245", "clave":"123", "id":250},
  {"rut":"123459253", "clave":"123", "id":251},
  {"rut":"123459261", "clave":"123", "id":252},
  {"rut":"12345927k", "clave":"123", "id":253},
  {"rut":"123459288", "clave":"123", "id":254},
  {"rut":"123459296", "clave":"123", "id":255},
  {"rut":"12345930k", "clave":"123", "id":256},
  {"rut":"123459318", "clave":"123", "id":257},
  {"rut":"123459326", "clave":"123", "id":258},
  {"rut":"123459334", "clave":"123", "id":259},
  {"rut":"123459342", "clave":"123", "id":260},
  {"rut":"123459350", "clave":"123", "id":261},
  {"rut":"123459369", "clave":"123", "id":262},
  {"rut":"123459377", "clave":"123", "id":263},
  {"rut":"123459385", "clave":"123", "id":264},
  {"rut":"123459393", "clave":"123", "id":265},
  {"rut":"123459407", "clave":"123", "id":266},
  {"rut":"123459415", "clave":"123", "id":267},
  {"rut":"123459423", "clave":"123", "id":268},
  {"rut":"123459431", "clave":"123", "id":269},
  {"rut":"12345944k", "clave":"123", "id":270},
  {"rut":"123459458", "clave":"123", "id":271},
  {"rut":"123459466", "clave":"123", "id":272},
  {"rut":"123459474", "clave":"123", "id":273},
  {"rut":"123459482", "clave":"123", "id":274},
  {"rut":"123459490", "clave":"123", "id":275},
  {"rut":"123459504", "clave":"123", "id":276},
  {"rut":"123459512", "clave":"123", "id":277},
  {"rut":"123459520", "clave":"123", "id":278},
  {"rut":"123459539", "clave":"123", "id":279},
  {"rut":"123459547", "clave":"123", "id":280},
  {"rut":"123459555", "clave":"123", "id":281},
  {"rut":"123459563", "clave":"123", "id":282},
  {"rut":"123459571", "clave":"123", "id":283},
  {"rut":"12345958k", "clave":"123", "id":284},
  {"rut":"123459598", "clave":"123", "id":285},
  {"rut":"123459601", "clave":"123", "id":286},
  {"rut":"12345961k", "clave":"123", "id":287},
  {"rut":"123459628", "clave":"123", "id":288},
  {"rut":"123459636", "clave":"123", "id":289},
  {"rut":"123459644", "clave":"123", "id":290},
  {"rut":"123459652", "clave":"123", "id":291},
  {"rut":"123459660", "clave":"123", "id":292},
  {"rut":"123459679", "clave":"123", "id":293},
  {"rut":"123459687", "clave":"123", "id":294},
  {"rut":"123459695", "clave":"123", "id":295},
  {"rut":"123459709", "clave":"123", "id":296},
  {"rut":"123459717", "clave":"123", "id":297},
  {"rut":"123459725", "clave":"123", "id":298},
  {"rut":"123459733", "clave":"123", "id":299},
  {"rut":"123459741", "clave":"123", "id":300},
  {"rut":"12345975k", "clave":"123", "id":301},
  {"rut":"123459768", "clave":"123", "id":302},
  {"rut":"123459776", "clave":"123", "id":303},
  {"rut":"123459784", "clave":"123", "id":304}]
